{
  "main": {
    "id": "5b764347d9b50a58",
    "type": "split",
    "children": [
      {
        "id": "ba38b5fe5e3791f3",
        "type": "tabs",
        "children": [
          {
            "id": "f18fa3a826c9575b",
            "type": "leaf",
            "state": {
              "type": "markdown",
              "state": {
                "file": "Record of my Life/Journals/Jan 23 journal.md",
                "mode": "source",
                "source": false
              }
            }
          },
          {
            "id": "c9fd2841c78e38a3",
            "type": "leaf",
            "state": {
              "type": "markdown",
              "state": {
                "file": "Record of my Life/Shopping Lists/Shopping list.md",
                "mode": "source",
                "source": false
              }
            }
          },
          {
            "id": "9ff7c7377a3e0868",
            "type": "leaf",
            "state": {
              "type": "markdown",
              "state": {
                "file": "Record of my Life/Schoolworks/Untitled.md",
                "mode": "source",
                "source": false
              }
            }
          },
          {
            "id": "04874b47cfab2744",
            "type": "leaf",
            "state": {
              "type": "markdown",
              "state": {
                "file": "What can I study for programming.md",
                "mode": "source",
                "source": false
              }
            }
          },
          {
            "id": "a49538de405623c1",
            "type": "leaf",
            "state": {
              "type": "markdown",
              "state": {
                "file": "Schedules/Jan 25 Schedule.md",
                "mode": "source",
                "source": false
              }
            }
          }
        ],
        "currentTab": 2
      }
    ],
    "direction": "vertical"
  },
  "left": {
    "id": "262b9ccc29835ee6",
    "type": "split",
    "children": [
      {
        "id": "fdb723fca2ac9222",
        "type": "tabs",
        "children": [
          {
            "id": "919fc80118a44109",
            "type": "leaf",
            "state": {
              "type": "file-explorer",
              "state": {
                "sortOrder": "alphabetical"
              }
            }
          },
          {
            "id": "e26bc652fd7f166f",
            "type": "leaf",
            "state": {
              "type": "search",
              "state": {
                "query": "",
                "matchingCase": false,
                "explainSearch": false,
                "collapseAll": false,
                "extraContext": false,
                "sortOrder": "alphabetical"
              }
            }
          },
          {
            "id": "bea91258172e4d74",
            "type": "leaf",
            "state": {
              "type": "bookmarks",
              "state": {}
            }
          }
        ]
      }
    ],
    "direction": "horizontal",
    "width": 300
  },
  "right": {
    "id": "59cc3278aa0338b3",
    "type": "split",
    "children": [
      {
        "id": "0dee4d0077a43a92",
        "type": "tabs",
        "children": [
          {
            "id": "c2e42ccb9ee0806a",
            "type": "leaf",
            "state": {
              "type": "tag",
              "state": {
                "sortOrder": "frequency",
                "useHierarchy": true
              }
            }
          },
          {
            "id": "6c11978258765848",
            "type": "leaf",
            "state": {
              "type": "outline",
              "state": {
                "file": "Record of my Life/Schoolworks/Untitled.md"
              }
            }
          },
          {
            "id": "fb18c0756e83f513",
            "type": "leaf",
            "state": {
              "type": "backlink",
              "state": {
                "file": "Record of my Life/Schoolworks/Untitled.md",
                "collapseAll": false,
                "extraContext": false,
                "sortOrder": "alphabetical",
                "showSearch": false,
                "searchQuery": "",
                "backlinkCollapsed": false,
                "unlinkedCollapsed": true
              }
            }
          },
          {
            "id": "8ff65b68327fd1f0",
            "type": "leaf",
            "state": {
              "type": "outgoing-link",
              "state": {
                "file": "Record of my Life/Schoolworks/Untitled.md",
                "linksCollapsed": false,
                "unlinkedCollapsed": true
              }
            }
          },
          {
            "id": "ea1c6c25197fe096",
            "type": "leaf",
            "state": {
              "type": "timeline",
              "state": {}
            }
          }
        ],
        "currentTab": 4
      }
    ],
    "direction": "horizontal",
    "width": 802.5
  },
  "left-ribbon": {
    "hiddenItems": {
      "switcher:Open quick switcher": false,
      "graph:Open graph view": false,
      "canvas:Create new canvas": false,
      "daily-notes:Open today's daily note": false,
      "templates:Insert template": false,
      "command-palette:Open command palette": false,
      "obsidian-day-planner:Timeline": false
    }
  },
  "active": "9ff7c7377a3e0868",
  "lastOpenFiles": [
    "Record of my Life/Schoolworks/Features list for coding our website.md",
    "Record of my Life/Schoolworks/Untitled.md",
    "Record of my Life/Journals/Jan 23 journal.md",
    "Record of my Life/Schoolworks/Schoolworks.md",
    "Record of my Life/Shopping Lists/Shopping list.md",
    "Record of my Life/Journals/Jan 27 Journal.md",
    "Record of my Life/Schoolworks",
    "conflict-files-obsidian-git.md",
    "images/studio-shot-isolated-on-gray-600nw-2287199651.webp",
    "images/Zeratul_SC2-LotV_Art1.webp",
    "images/Untitled 6.jpg",
    "images/Untitled 5.jpg",
    "images/Bernini_Hl._Longinus_Petersdom.jpg",
    "images/600px-Zeratul.jpg",
    "images/422396533_343300882015851_7065555722195853375_n.jpg",
    "images/11-8.jpg",
    "Schedules/Jan 25 Schedule ( Supposed Weights day ).md",
    "Record of my Life/Journals/Jan 25 Journal.md",
    "Project Alaska/Characters/Untitled.canvas",
    "Project Alaska/Characters/Sa'lanzo.md",
    "Record of my Life/Journals/Untitled.md",
    "Record of my Life/Journals/Jan 24 Journal.md",
    "Schedules/Jan 24 Schedule.md",
    "Schedules/Jan 26 Schedule.md",
    "Schedules/Jan 25 Schedule.md",
    "What can I study for programming.md",
    "Schedules/Jan 23 Schedule.md",
    "images/wh40k__adepta_sororitas__by_bergionstyle_dg25h2u-fullview.jpg",
    "images/viking-raiders-in-ocean.jpg",
    "Schedules",
    "Record of my Life/Journals/2024-01-23.md",
    "Project Alaska/Factions, Orders, and Groups/Roselande.canvas",
    "Project Alaska/Factions, Orders, and Groups/Roselande Corsairs.md",
    "Project Alaska/Factions, Orders, and Groups/Pullerng Order.md",
    "Project Alaska/Factions, Orders, and Groups/Pullerng Order.canvas",
    "Project Alaska/Cities, Nations, and Villages/Site 113-b.md",
    "Project Alaska/Cities, Nations, and Villages/Site 113-b.canvas",
    "Project Alaska/Characters/Jhin-girl Belle.md",
    "Project Alaska/Characters/Jhin-girl Belle.canvas",
    "Project Alaska/Factions, Orders, and Groups",
    "Project Alaska/Cities, Nations, and Villages",
    "Project Alaska/Characters",
    "Project Alaska",
    "Fitness/Training plan..md",
    "Fitness/Training Canvas.canvas",
    "Fitness/The point of my Training.md",
    "Fitness/Jan 24 ( Wednesday - Cardio day ).md",
    "Fitness",
    "2024-01-23.md",
    "images",
    "Record of my Life/Bible Study ( Catholicism )",
    "Record of my Life/Shopping Lists"
  ]
}